LICENSE.txt
MANIFEST.in
README.md
setup.cfg
setup.py
rongdaVbaAddins/RDaddins.xlam
rongdaVbaAddins/RecentTime.db
rongdaVbaAddins/__init__.py
rongdaVbaAddins/registerCode.pyd
rongdaVbaAddins/rongdavbaaddins.pyd
rongdaVbaAddins/runregiterCode.py
rongdaVbaAddins/文件处理类模板.xlsx
rongdaVbaAddins/Function/__init__.py
rongdaVbaAddins/Function/minusFunction.pyd
rongdaVbaAddins/Function/minusFunctionpy.py
rongdaVbaAddins/Ui/__init__.py
rongdaVbaAddins/Ui/rongdaVbaAddinsUi.pyd
rongdaVbaAddins/package/__init__.py
rongdaVbaAddins/package/pyzipper/__init__.py
rongdaVbaAddins/package/pyzipper/__version__.py
rongdaVbaAddins/package/pyzipper/zipfile.py
rongdaVbaAddins/package/pyzipper/zipfile_aes.py
rongdavbaaddins.egg-info/PKG-INFO
rongdavbaaddins.egg-info/SOURCES.txt
rongdavbaaddins.egg-info/dependency_links.txt
rongdavbaaddins.egg-info/top_level.txt